{
  "section_index": 8,
  "section_name": "jxl-policy",
  "tasks": [
    {
      "task_id": "008-errors-2",
      "finding_id": "errors-2",
      "finding_type": "issue",
      "file": "packages/jxl-policy/src/index.ts",
      "line_start": 127,
      "line_end": 131,
      "title": "downsampleForContainer returns wrong result for non-integer or very large ratio due to truncating bitwise cast",
      "category": "numeric-edge-case",
      "severity": "medium",
      "depends_on": [],
      "tier": "haiku",
      "task_kind": "direct_fix",
      "reason_for_tier": "trivial arithmetic guard change: replace `ratio | 0` with clamped Math.floor or add upper-bound clamp before the bitwise op",
      "status": "pending"
    },
    {
      "task_id": "008-errors-3",
      "finding_id": "errors-3",
      "finding_type": "issue",
      "file": "packages/jxl-policy/src/index.ts",
      "line_start": 122,
      "line_end": 132,
      "title": "downsampleForContainer does not guard against NaN or Infinity inputs",
      "category": "missing-input-validation",
      "severity": "low",
      "depends_on": ["008-errors-2"],
      "tier": "haiku",
      "task_kind": "direct_fix",
      "reason_for_tier": "trivial guard change: replace `<= 0` with `!Number.isFinite(x) || x <= 0` for all four parameters; same site as errors-2",
      "status": "pending"
    },
    {
      "task_id": "008-contracts-1",
      "finding_id": "contracts-1",
      "finding_type": "issue",
      "file": "packages/jxl-policy/src/index.ts",
      "line_start": 129,
      "line_end": 132,
      "title": "downsampleForContainer returns an invalid Downsample cast when ratio|0 overflows to 0 (NaN or Infinity input)",
      "category": "type-safety / return-shape drift",
      "severity": "medium",
      "depends_on": ["008-errors-2", "008-errors-3"],
      "tier": "haiku",
      "task_kind": "direct_fix",
      "reason_for_tier": "same root-cause fix as errors-2/errors-3; adding a post-compute clamp or runtime assertion at return site is trivial",
      "status": "pending"
    },
    {
      "task_id": "008-logic-4",
      "finding_id": "logic-4",
      "finding_type": "opportunity",
      "file": "packages/jxl-policy/src/index.ts",
      "line_start": 127,
      "line_end": 131,
      "title": "downsampleForContainer return type is structurally unchecked: no assertion that result is 1|2|4|8",
      "category": "invariant-checking",
      "severity": "low",
      "depends_on": ["008-errors-2", "008-errors-3"],
      "tier": "haiku",
      "task_kind": "direct_fix",
      "reason_for_tier": "trivial: add a single runtime assertion or clamp at the return site after the NaN/overflow fix",
      "status": "pending"
    },
    {
      "task_id": "008-errors-6",
      "finding_id": "errors-6",
      "finding_type": "issue",
      "file": "packages/jxl-policy/test/policy.test.ts",
      "line_start": 133,
      "line_end": 154,
      "title": "downsampleForContainer tests do not cover NaN or very-large-ratio inputs that cause integer overflow",
      "category": "missing-test-coverage",
      "severity": "low",
      "depends_on": ["008-errors-2", "008-errors-3", "008-contracts-1"],
      "tier": "haiku",
      "task_kind": "direct_fix",
      "reason_for_tier": "trivial test additions; these cases are directly motivated by the confirmed errors-2/errors-3 bugs",
      "status": "pending"
    },
    {
      "task_id": "008-logic-3",
      "finding_id": "logic-3",
      "finding_type": "opportunity",
      "file": "packages/jxl-policy/test/policy.test.ts",
      "line_start": 133,
      "line_end": 154,
      "title": "downsampleForContainer test suite missing: mismatched-aspect-ratio case, ratio-exactly-3 boundary, and non-square containers",
      "category": "test-coverage",
      "severity": "low",
      "depends_on": [],
      "tier": "haiku",
      "task_kind": "direct_fix",
      "reason_for_tier": "trivial test additions covering asymmetric container and non-power-of-two ratio boundary",
      "status": "pending"
    },
    {
      "task_id": "008-errors-5",
      "finding_id": "errors-5",
      "finding_type": "opportunity",
      "file": "packages/jxl-policy/src/index.ts",
      "line_start": 58,
      "line_end": 58,
      "title": "Policy errors use bare RangeError with no error code, making programmatic handling harder for callers",
      "category": "no-error-taxonomy",
      "severity": "info",
      "depends_on": [],
      "tier": "haiku",
      "task_kind": "direct_fix",
      "reason_for_tier": "trivial: add a `.code` property to the thrown RangeError instances; non-breaking",
      "status": "pending"
    },
    {
      "task_id": "008-contracts-5",
      "finding_id": "contracts-5",
      "finding_type": "opportunity",
      "file": "packages/jxl-policy/test/policy.test.ts",
      "line_start": 1,
      "line_end": 155,
      "title": "No test covers round-trip invariant: applyDecodePolicy output is a valid DecodeOptions accepted by the scheduler/session without further transformation",
      "category": "no contract testing / schema validation at boundary",
      "severity": "medium",
      "depends_on": [],
      "tier": "sonnet",
      "task_kind": "adr_draft",
      "reason_for_tier": "requires understanding the DecodeOptions/EncodeOptions types from jxl-session/jxl-scheduler to write a meaningful cross-package structural check",
      "status": "pending"
    },
    {
      "task_id": "008-errors-4",
      "finding_id": "errors-4",
      "finding_type": "issue",
      "file": "packages/jxl-policy/src/index.ts",
      "line_start": 55,
      "line_end": 73,
      "title": "applyDecodePolicy and applyEncodePolicy accept null base without throwing, silently spreading null",
      "category": "missing-input-validation",
      "severity": "low",
      "depends_on": [],
      "tier": "sonnet",
      "task_kind": "direct_fix",
      "reason_for_tier": "uncertain verdict; requires deciding whether JS/dynamic callers are an intended audience before adding a null guard",
      "status": "pending"
    }
  ],
  "counts": {
    "total": 13,
    "pending": 9,
    "deferred": 4,
    "issue": 7,
    "opportunity": 6,
    "direct_fix": 8,
    "adr_draft": 1,
    "haiku": 7,
    "sonnet": 2,
    "opus": 0
  }
}
